big_dict_energy/__init__.py
big_dict_energy/lm_setup.py
big_dict_energy/pipeline.py
big_dict_energy/processors.py
big_dict_energy/steps.py
big_dict_energy/utils/__init__.py
big_dict_energy/utils/logging.py
big_dict_energy/utils/text_utils.py
big_dict_energy-0.1.0.dist-info/METADATA
big_dict_energy-0.1.0.dist-info/WHEEL
big_dict_energy-0.1.0.dist-info/top_level.txt
big_dict_energy-0.1.0.dist-info/RECORD
