Metadata-Version: 2.2
Name: big_dict_energy
Version: 0.1.0
Summary: A composable language model workflow builder for DSPy with dictionary-based data storage
Author-email: Christian D'Andrea <crdandre@gmail.com>
License: MIT
Requires-Python: >=3.10
Requires-Dist: dspy==2.5.43
Requires-Dist: pyyaml
Provides-Extra: dev
Requires-Dist: bumpver~=2023.1129; extra == "dev"
Requires-Dist: pre-commit~=3.5; extra == "dev"
Requires-Dist: ruff~=0.9.2; extra == "dev"
Provides-Extra: test
Requires-Dist: pytest~=7.4; extra == "test"
